derive_event/__init__.py
derive_event/derive.py
derive_event_pm4py-1.0.1.dist-info/LICENSE
derive_event_pm4py-1.0.1.dist-info/METADATA
derive_event_pm4py-1.0.1.dist-info/WHEEL
derive_event_pm4py-1.0.1.dist-info/entry_points.txt
derive_event_pm4py-1.0.1.dist-info/top_level.txt
derive_event_pm4py-1.0.1.dist-info/RECORD
