Metadata-Version: 2.1
Name: derive-event-pm4py
Version: 1.0.1
Summary: It derives new events based on rules provided as inputs.
Home-page: https://github.com/ajayp10/derive_event_pm4py
Author: Ajay Pandi
Author-email: ajay.pandi@rwth-aachen.de
License: MIT
Platform: UNKNOWN
Classifier: License :: OSI Approved :: MIT License
Classifier: Programming Language :: Python :: 3.7
Classifier: Programming Language :: Python :: 3.8
Requires-Dist: pandas
Requires-Dist: numpy
Requires-Dist: pm4py
